cyclonedx_py/__init__.py
cyclonedx_py/__main__.py
cyclonedx_py/_internal/__init__.py
cyclonedx_py/_internal/cli.py
cyclonedx_py/_internal/cli_common.py
cyclonedx_py/_internal/environment.py
cyclonedx_py/_internal/pipenv.py
cyclonedx_py/_internal/poetry.py
cyclonedx_py/_internal/py_interop/__init__.py
cyclonedx_py/_internal/py_interop/glob.py
cyclonedx_py/_internal/py_interop/packagemetadata.py
cyclonedx_py/_internal/requirements.py
cyclonedx_py/_internal/utils/__init__.py
cyclonedx_py/_internal/utils/args.py
cyclonedx_py/_internal/utils/bytes.py
cyclonedx_py/_internal/utils/cdx.py
cyclonedx_py/_internal/utils/io.py
cyclonedx_py/_internal/utils/license_trove_classifier.py
cyclonedx_py/_internal/utils/mimetypes.py
cyclonedx_py/_internal/utils/packaging.py
cyclonedx_py/_internal/utils/pep610.py
cyclonedx_py/_internal/utils/pep621.py
cyclonedx_py/_internal/utils/pep639.py
cyclonedx_py/_internal/utils/poetry.py
cyclonedx_py/_internal/utils/pyproject.py
cyclonedx_py/_internal/utils/secret.py
cyclonedx_py/_internal/utils/toml.py
cyclonedx_py/py.typed
cyclonedx_bom-7.2.0.dist-info/METADATA
cyclonedx_bom-7.2.0.dist-info/WHEEL
cyclonedx_bom-7.2.0.dist-info/entry_points.txt
cyclonedx_bom-7.2.0.dist-info/licenses/LICENSE
cyclonedx_bom-7.2.0.dist-info/licenses/NOTICE
cyclonedx_bom-7.2.0.dist-info/RECORD
