Metadata-Version: 2.4
Name: cyclonedx-bom
Version: 7.2.0
Summary: CycloneDX Software Bill of Materials (SBOM) generator for Python projects and environments
License: Apache-2.0
License-File: LICENSE
License-File: NOTICE
Keywords: OWASP,CycloneDX,bill-of-materials,BOM,software-bill-of-materials,SBOM,environment,virtualenv,venv,Poetry,Pipenv,requirements,PDM,Conda,SPDX,licenses,PURL,package-url,dependency-graph
Author: Jan Kowalleck
Author-email: jan.kowalleck@gmail.com
Maintainer: Jan Kowalleck
Maintainer-email: jan.kowalleck@gmail.com
Requires-Python: >=3.9,<4.0
Classifier: Development Status :: 5 - Production/Stable
Classifier: Environment :: Console
Classifier: Intended Audience :: Developers
Classifier: Intended Audience :: Information Technology
Classifier: Intended Audience :: Legal Industry
Classifier: Intended Audience :: System Administrators
Classifier: License :: OSI Approved :: Apache Software License
Classifier: Programming Language :: Python :: 3
Classifier: Programming Language :: Python :: 3.9
Classifier: Programming Language :: Python :: 3.10
Classifier: Programming Language :: Python :: 3.11
Classifier: Programming Language :: Python :: 3.12
Classifier: Programming Language :: Python :: 3.13
Classifier: Programming Language :: Python :: 3.14
Classifier: Topic :: Security
Classifier: Topic :: Software Development
Classifier: Topic :: System :: Software Distribution
Classifier: Typing :: Typed
Requires-Dist: chardet (>=5.1,<6.0)
Requires-Dist: cyclonedx-python-lib[validation] (>=8.0,<12)
Requires-Dist: packageurl-python (>=0.11,<2)
Requires-Dist: packaging (>=22,<26)
Requires-Dist: pip-requirements-parser (>=32.0,<33.0)
Requires-Dist: tomli (>=2.0.1,<3.0.0) ; python_version < "3.11"
Project-URL: Bug Tracker, https://github.com/CycloneDX/cyclonedx-python/issues
Project-URL: Changelog, https://github.com/CycloneDX/cyclonedx-python/releases
Project-URL: Documentation, https://cyclonedx-bom-tool.readthedocs.io/
Project-URL: Funding, https://owasp.org/donate/?reponame=www-project-cyclonedx&title=OWASP+CycloneDX
Project-URL: Homepage, https://github.com/CycloneDX/cyclonedx-python/#readme
Project-URL: Repository, https://github.com/CycloneDX/cyclonedx-python/
